apikeyrotator/__init__.py
apikeyrotator/core/__init__.py
apikeyrotator/core/config_loader.py
apikeyrotator/core/exceptions.py
apikeyrotator/core/key_parser.py
apikeyrotator/core/rotator.py
apikeyrotator/metrics/__init__.py
apikeyrotator/metrics/collector.py
apikeyrotator/metrics/exporters.py
apikeyrotator/metrics/models.py
apikeyrotator/middleware/__init__.py
apikeyrotator/middleware/base.py
apikeyrotator/middleware/caching.py
apikeyrotator/middleware/logging.py
apikeyrotator/middleware/models.py
apikeyrotator/middleware/rate_limit.py
apikeyrotator/middleware/retry.py
apikeyrotator/providers/__init__.py
apikeyrotator/providers/aws.py
apikeyrotator/providers/base.py
apikeyrotator/providers/environment.py
apikeyrotator/providers/factory.py
apikeyrotator/providers/file.py
apikeyrotator/providers/gcp.py
apikeyrotator/strategies/__init__.py
apikeyrotator/strategies/base.py
apikeyrotator/strategies/factory.py
apikeyrotator/strategies/health_based.py
apikeyrotator/strategies/lru.py
apikeyrotator/strategies/random.py
apikeyrotator/strategies/round_robin.py
apikeyrotator/strategies/weighted.py
apikeyrotator/utils/__init__.py
apikeyrotator/utils/error_classifier.py
apikeyrotator/utils/retry.py
apikeyrotator-0.5.1.dist-info/METADATA
apikeyrotator-0.5.1.dist-info/WHEEL
apikeyrotator-0.5.1.dist-info/entry_points.txt
apikeyrotator-0.5.1.dist-info/licenses/LICENSE
apikeyrotator-0.5.1.dist-info/RECORD
