Metadata-Version: 2.4
Name: apikeyrotator
Version: 0.5.1
Summary: 🚀 Powerful and simple API key rotator for bypassing rate limits and handling errors
Project-URL: Homepage, https://github.com/PrimeevolutionZ/apikeyrotator
Project-URL: Documentation, https://github.com/PrimeevolutionZ/apikeyrotator#readme
Project-URL: Repository, https://github.com/PrimeevolutionZ/apikeyrotator
Project-URL: Source Code, https://github.com/PrimeevolutionZ/apikeyrotator
Project-URL: Bug Tracker, https://github.com/PrimeevolutionZ/apikeyrotator/issues
Project-URL: Issue Tracker, https://github.com/PrimeevolutionZ/apikeyrotator/issues
Project-URL: Changelog, https://github.com/PrimeevolutionZ/apikeyrotator/releases
Project-URL: Discussions, https://github.com/PrimeevolutionZ/apikeyrotator/discussions
Author-email: Prime Evolution <develop@eclips-team.ru>
Maintainer-email: Prime Evolution <develop@eclips-team.ru>
License: MIT
License-File: LICENSE
Keywords: aiohttp,api,api-keys,async,circuit-breaker,http-client,load-balancing,metrics,middleware,monitoring,rate-limit,requests,retry,rotation
Classifier: Development Status :: 4 - Beta
Classifier: Intended Audience :: Developers
Classifier: Intended Audience :: Information Technology
Classifier: Intended Audience :: System Administrators
Classifier: License :: OSI Approved :: MIT License
Classifier: Operating System :: OS Independent
Classifier: Programming Language :: Python
Classifier: Programming Language :: Python :: 3
Classifier: Programming Language :: Python :: 3 :: Only
Classifier: Programming Language :: Python :: 3.9
Classifier: Programming Language :: Python :: 3.10
Classifier: Programming Language :: Python :: 3.11
Classifier: Programming Language :: Python :: 3.12
Classifier: Programming Language :: Python :: Implementation :: CPython
Classifier: Topic :: Internet :: WWW/HTTP
Classifier: Topic :: Software Development :: Libraries :: Python Modules
Classifier: Topic :: System :: Networking
Classifier: Topic :: Utilities
Classifier: Typing :: Typed
Requires-Python: >=3.8
Requires-Dist: aiohttp<4.0.0,>=3.8.0
Requires-Dist: python-dotenv<2.0.0,>=1.0.0
Requires-Dist: pyyaml<7.0.0,>=6.0
Requires-Dist: requests<3.0.0,>=2.28.0
Provides-Extra: all
Requires-Dist: aioresponses>=0.7.4; extra == 'all'
Requires-Dist: black>=23.7.0; extra == 'all'
Requires-Dist: boto3<2.0.0,>=1.28.0; extra == 'all'
Requires-Dist: google-cloud-secret-manager<3.0.0,>=2.16.0; extra == 'all'
Requires-Dist: mkdocs-material>=9.2.0; extra == 'all'
Requires-Dist: mkdocs>=1.5.0; extra == 'all'
Requires-Dist: mkdocstrings[python]>=0.22.0; extra == 'all'
Requires-Dist: mypy>=1.5.0; extra == 'all'
Requires-Dist: pre-commit>=3.3.0; extra == 'all'
Requires-Dist: pytest-asyncio>=0.21.0; extra == 'all'
Requires-Dist: pytest-cov>=4.1.0; extra == 'all'
Requires-Dist: pytest-mock>=3.11.0; extra == 'all'
Requires-Dist: pytest>=7.4.0; extra == 'all'
Requires-Dist: requests-mock>=1.11.0; extra == 'all'
Requires-Dist: ruff>=0.0.287; extra == 'all'
Requires-Dist: types-requests>=2.31.0; extra == 'all'
Provides-Extra: aws
Requires-Dist: boto3<2.0.0,>=1.28.0; extra == 'aws'
Provides-Extra: dev
Requires-Dist: aioresponses>=0.7.4; extra == 'dev'
Requires-Dist: black>=23.7.0; extra == 'dev'
Requires-Dist: mypy>=1.5.0; extra == 'dev'
Requires-Dist: pre-commit>=3.3.0; extra == 'dev'
Requires-Dist: pytest-asyncio>=0.21.0; extra == 'dev'
Requires-Dist: pytest-cov>=4.1.0; extra == 'dev'
Requires-Dist: pytest-mock>=3.11.0; extra == 'dev'
Requires-Dist: pytest>=7.4.0; extra == 'dev'
Requires-Dist: requests-mock>=1.11.0; extra == 'dev'
Requires-Dist: ruff>=0.0.287; extra == 'dev'
Requires-Dist: types-requests>=2.31.0; extra == 'dev'
Provides-Extra: docs
Requires-Dist: mkdocs-material>=9.2.0; extra == 'docs'
Requires-Dist: mkdocs>=1.5.0; extra == 'docs'
Requires-Dist: mkdocstrings[python]>=0.22.0; extra == 'docs'
Provides-Extra: gcp
Requires-Dist: google-cloud-secret-manager<3.0.0,>=2.16.0; extra == 'gcp'
Provides-Extra: test
Requires-Dist: aioresponses>=0.7.4; extra == 'test'
Requires-Dist: pytest-asyncio>=0.21.0; extra == 'test'
Requires-Dist: pytest-cov>=4.1.0; extra == 'test'
Requires-Dist: pytest-mock>=3.11.0; extra == 'test'
Requires-Dist: pytest>=7.4.0; extra == 'test'
Requires-Dist: requests-mock>=1.11.0; extra == 'test'
